feedsubs/__init__.py
feedsubs/manage.py
feedsubs/urls.py
feedsubs/wsgi.py
feedsubs/__pycache__/__init__.cpython-36.pyc
feedsubs/__pycache__/manage.cpython-36.pyc
feedsubs/__pycache__/urls.cpython-36.pyc
feedsubs/__pycache__/wsgi.cpython-36.pyc
feedsubs/settings/__init__.py
feedsubs/settings/base.py
feedsubs/settings/dev.py
feedsubs/settings/prod.py
feedsubs/settings/__pycache__/__init__.cpython-36.pyc
feedsubs/settings/__pycache__/base.cpython-36.pyc
feedsubs/settings/__pycache__/dev.cpython-36.pyc
feedsubs/settings/__pycache__/prod.cpython-36.pyc
feedsubs/static/feedsubs/favicon.ico
feedsubs/static/feedsubs/feedsubs.js
feedsubs/static/feedsubs/logo.svg
feedsubs/static/feedsubs/vendor/bulma-tagsinput.min.css
feedsubs/static/feedsubs/vendor/bulma-tagsinput.min.js
feedsubs/static/feedsubs/vendor/jquery-3.3.1.min.js
feedsubs/static/feedsubs/vendor/bulmaswatch/superhero.min.css
feedsubs/static/feedsubs/vendor/fontawesome/css/all.min.css
feedsubs/static/feedsubs/vendor/fontawesome/webfonts/fa-brands-400.eot
feedsubs/static/feedsubs/vendor/fontawesome/webfonts/fa-brands-400.svg
feedsubs/static/feedsubs/vendor/fontawesome/webfonts/fa-brands-400.ttf
feedsubs/static/feedsubs/vendor/fontawesome/webfonts/fa-brands-400.woff
feedsubs/static/feedsubs/vendor/fontawesome/webfonts/fa-brands-400.woff2
feedsubs/static/feedsubs/vendor/fontawesome/webfonts/fa-regular-400.eot
feedsubs/static/feedsubs/vendor/fontawesome/webfonts/fa-regular-400.svg
feedsubs/static/feedsubs/vendor/fontawesome/webfonts/fa-regular-400.ttf
feedsubs/static/feedsubs/vendor/fontawesome/webfonts/fa-regular-400.woff
feedsubs/static/feedsubs/vendor/fontawesome/webfonts/fa-regular-400.woff2
feedsubs/static/feedsubs/vendor/fontawesome/webfonts/fa-solid-900.eot
feedsubs/static/feedsubs/vendor/fontawesome/webfonts/fa-solid-900.svg
feedsubs/static/feedsubs/vendor/fontawesome/webfonts/fa-solid-900.ttf
feedsubs/static/feedsubs/vendor/fontawesome/webfonts/fa-solid-900.woff
feedsubs-0.0.2.dist-info/LICENSE
feedsubs-0.0.2.dist-info/METADATA
feedsubs-0.0.2.dist-info/WHEEL
feedsubs-0.0.2.dist-info/entry_points.txt
feedsubs-0.0.2.dist-info/top_level.txt
feedsubs-0.0.2.dist-info/RECORD
