Metadata-Version: 2.1
Name: feedsubs
Version: 0.0.2
Summary: RSS feed reader for Python 3
Home-page: https://github.com/NicolasLM/feedsubs
Author: Nicolas Le Manchet
Author-email: nicolas@lemanchet.fr
License: MIT
Keywords: rss atom json feed feeds reader
Platform: UNKNOWN
Classifier: Development Status :: 4 - Beta
Classifier: Intended Audience :: End Users/Desktop
Classifier: License :: OSI Approved :: MIT License
Classifier: Natural Language :: English
Classifier: Operating System :: OS Independent
Classifier: Environment :: Web Environment
Classifier: Programming Language :: Python
Classifier: Programming Language :: Python :: 3
Classifier: Programming Language :: Python :: 3 :: Only
Classifier: Programming Language :: Python :: 3.6
Classifier: Programming Language :: Python :: 3.7
Classifier: Topic :: Internet :: WWW/HTTP
Classifier: Topic :: Internet :: WWW/HTTP :: Dynamic Content
Classifier: Topic :: Internet :: WWW/HTTP :: Dynamic Content :: News/Diary
Classifier: Framework :: Django
Requires-Dist: django
Requires-Dist: django-allauth
Requires-Dist: django-bulma
Requires-Dist: atoma
Requires-Dist: bleach
Requires-Dist: beautifulsoup4
Requires-Dist: psycopg2
Requires-Dist: requests
Requires-Dist: spinach
Requires-Dist: Pillow
Requires-Dist: python-decouple
Provides-Extra: dev
Requires-Dist: django-debug-toolbar ; extra == 'dev'
Requires-Dist: pycodestyle ; extra == 'dev'
Requires-Dist: pytest ; extra == 'dev'
Requires-Dist: pytest-cov ; extra == 'dev'
Requires-Dist: pytest-django ; extra == 'dev'
Provides-Extra: prod
Requires-Dist: boto3 ; extra == 'prod'
Requires-Dist: ddtrace ; extra == 'prod'
Requires-Dist: django-redis ; extra == 'prod'
Requires-Dist: django-storages ; extra == 'prod'
Requires-Dist: django-xff ; extra == 'prod'
Requires-Dist: waitress ; extra == 'prod'
Requires-Dist: whitenoise ; extra == 'prod'
Requires-Dist: raven ; extra == 'prod'
